README.md
setup.cfg
setup.py
megaoptim/__init__.py
megaoptim/_version.py
megaoptim.egg-info/PKG-INFO
megaoptim.egg-info/SOURCES.txt
megaoptim.egg-info/dependency_links.txt
megaoptim.egg-info/entry_points.txt
megaoptim.egg-info/requires.txt
megaoptim.egg-info/top_level.txt
megaoptim/cli/__init__.py
megaoptim/cli/cli.py
megaoptim/client/__init__.py
megaoptim/client/client.py